setup.py
copads/Array.py
copads/Bag.py
copads/ColorMap.py
copads/Constants.py
copads/CopadsExceptions.py
copads/Graph.py
copads/HypothesisTest.py
copads/Matrix.py
copads/NRPy.py
copads/ObjectDistance.py
copads/Operations.py
copads/PriorityDictionary.py
copads/RingStructure.py
copads/SampleStatistics.py
copads/Set.py
copads/StatisticsDistribution.py
copads/Tree.py
copads/TreeNodes.py
copads/__init__.py
copads.egg-info/PKG-INFO
copads.egg-info/SOURCES.txt
copads.egg-info/dependency_links.txt
copads.egg-info/top_level.txt
test/GraphTest.py
test/HypothesisTestTest.py
test/MatrixTest.py
test/NRTest.py
test/ObjectDistanceTest.py
test/OperationsTest.py
test/RBTreeTest.py
test/StatDistribTest.py
test/__init__.py
test/tharness.py