Metadata-Version: 1.0
Name: copads
Version: 0.2
Summary: Collection of Python Algorithms and Data Structures
Home-page: http://copads.sourceforge.net
Author: Maurice HT Ling
Author-email: mauriceling@acm.org
License: GNU Lesser General Public License version 3
Platform: UNKNOWN
Classifier: Development Status :: 3 - Alpha
Classifier: Intended Audience :: Developers
Classifier: License :: OSI Approved :: GNU Library or Lesser General Public License (LGPL)
Classifier: Operating System :: OS Independent
Classifier: Programming Language :: Python
Classifier: Topic :: Scientific/Engineering :: Artificial Intelligence
Classifier: Topic :: Scientific/Engineering :: Mathematics
Classifier: Topic :: Software Development :: Libraries :: Python Modules
